glean/indexing/__init__.py
glean/indexing/models.py
glean/indexing/py.typed
glean/indexing/common/__init__.py
glean/indexing/common/batch_processor.py
glean/indexing/common/content_formatter.py
glean/indexing/common/glean_client.py
glean/indexing/common/metrics.py
glean/indexing/common/mocks.py
glean/indexing/common/property_definition_builder.py
glean/indexing/connectors/__init__.py
glean/indexing/connectors/base_connector.py
glean/indexing/connectors/base_data_client.py
glean/indexing/connectors/base_datasource_connector.py
glean/indexing/connectors/base_people_connector.py
glean/indexing/connectors/base_streaming_data_client.py
glean/indexing/connectors/base_streaming_datasource_connector.py
glean/indexing/observability/__init__.py
glean/indexing/observability/observability.py
glean/indexing/testing/__init__.py
glean/indexing/testing/connector_test_harness.py
glean/indexing/testing/mock_data_source.py
glean/indexing/testing/mock_glean_client.py
glean/indexing/testing/response_validator.py
glean_indexing_sdk-0.2.0.dist-info/METADATA
glean_indexing_sdk-0.2.0.dist-info/WHEEL
glean_indexing_sdk-0.2.0.dist-info/licenses/LICENSE
glean_indexing_sdk-0.2.0.dist-info/RECORD
