Metadata-Version: 2.4
Name: glean-indexing-sdk
Version: 0.2.0
Summary: SDK for building custom Glean indexing integrations
Project-URL: Source Code, https://github.com/glean-io/glean-indexing-sdk
Author-email: Steve Calvert <steve.calvert@glean.com>
License: MIT
License-File: LICENSE
Requires-Python: <4.0,>=3.10
Requires-Dist: glean-api-client>=0.6.3
Requires-Dist: jinja2>=3.1.2
Provides-Extra: dev
Requires-Dist: build>=1.0.0; extra == 'dev'
Requires-Dist: commitizen>=4.4.1; extra == 'dev'
Requires-Dist: pip-audit>=2.6.0; extra == 'dev'
Requires-Dist: twine>=4.0.0; extra == 'dev'
Provides-Extra: lint
Requires-Dist: ruff>=0.5; extra == 'lint'
Provides-Extra: test
Requires-Dist: pytest-asyncio>=0.23.2; extra == 'test'
Requires-Dist: pytest-cov>=4.1.0; extra == 'test'
Requires-Dist: pytest-httpx>=0.35.0; extra == 'test'
Requires-Dist: pytest-socket>=0.7.0; extra == 'test'
Requires-Dist: pytest-watcher>=0.3.4; extra == 'test'
Requires-Dist: pytest>=7.4.3; extra == 'test'
Requires-Dist: python-dotenv>=1.1.0; extra == 'test'
Provides-Extra: typing
Requires-Dist: pyright>=1.1.370; extra == 'typing'
